paderbox/__init__.py
paderbox/notebook.py
paderbox/array/__init__.py
paderbox/array/context.py
paderbox/array/intervall.py
paderbox/array/padding.py
paderbox/array/rearrange.py
paderbox/array/segment.py
paderbox/array/sparse.py
paderbox/array/interval/__init__.py
paderbox/array/interval/core.py
paderbox/array/interval/kaldi.py
paderbox/array/interval/rttm.py
paderbox/array/interval/util.cp38-win32.pyd
paderbox/io/__init__.py
paderbox/io/atomic.py
paderbox/io/audioread.py
paderbox/io/audiowrite.py
paderbox/io/cache.py
paderbox/io/cache_dir.py
paderbox/io/cache_loader.py
paderbox/io/csv_module.py
paderbox/io/data_dir.py
paderbox/io/download.py
paderbox/io/file_handling.py
paderbox/io/hdf5.py
paderbox/io/json_module.py
paderbox/io/new_subdir.py
paderbox/io/path_utils.py
paderbox/io/play.py
paderbox/io/wrapper_dump.py
paderbox/io/wrapper_load.py
paderbox/io/yaml_module.py
paderbox/math/__init__.py
paderbox/math/directional.py
paderbox/math/rotation.py
paderbox/math/scalar.py
paderbox/math/solve.py
paderbox/math/vector.py
paderbox/testing/__init__.py
paderbox/testing/attr.py
paderbox/testing/condition.py
paderbox/testing/doctest_compare.py
paderbox/testing/module_asserts.py
paderbox/testing/testfile_fetcher.py
paderbox/transform/__init__.py
paderbox/transform/module_fbank.py
paderbox/transform/module_filter.py
paderbox/transform/module_mfcc.py
paderbox/transform/module_normalize.py
paderbox/transform/module_phase_features.py
paderbox/transform/module_phase_reconstruction.py
paderbox/transform/module_resample.py
paderbox/transform/module_stft.py
paderbox/utils/__init__.py
paderbox/utils/debug_utils.py
paderbox/utils/deprecation.py
paderbox/utils/dtw.py
paderbox/utils/functional.py
paderbox/utils/iterable.py
paderbox/utils/mapping.py
paderbox/utils/matlab.py
paderbox/utils/misc.py
paderbox/utils/nested.py
paderbox/utils/numpy_utils.py
paderbox/utils/pandas_utils.py
paderbox/utils/pretty.py
paderbox/utils/process_caller.py
paderbox/utils/profiling.py
paderbox-0.0.5.dist-info/LICENSE
paderbox-0.0.5.dist-info/METADATA
paderbox-0.0.5.dist-info/WHEEL
paderbox-0.0.5.dist-info/entry_points.txt
paderbox-0.0.5.dist-info/top_level.txt
paderbox-0.0.5.dist-info/RECORD
